jhcalc/calculator.py
junhyeok31-0.0.1.dist-info/LICENSE
junhyeok31-0.0.1.dist-info/METADATA
junhyeok31-0.0.1.dist-info/WHEEL
junhyeok31-0.0.1.dist-info/top_level.txt
junhyeok31-0.0.1.dist-info/RECORD
