Metadata-Version: 2.1
Name: junhyeok31
Version: 0.0.1
Summary: nice calculator
Home-page: https://github.com/junhyeok31/calc0001
Download-URL: https://github.com/junhyeok31/calc0001/
Author: jhson
Classifier: Programming Language :: Python :: 3
License-File: LICENSE
